bicleaner_hardrules-2.10.8.data/data/bin/build_binary
bicleaner_hardrules-2.10.8.data/data/bin/count_ngrams
bicleaner_hardrules-2.10.8.data/data/bin/filter
bicleaner_hardrules-2.10.8.data/data/bin/fragment
bicleaner_hardrules-2.10.8.data/data/bin/kenlm_benchmark
bicleaner_hardrules-2.10.8.data/data/bin/lmplz
bicleaner_hardrules-2.10.8.data/data/bin/phrase_table_vocab
bicleaner_hardrules-2.10.8.data/data/bin/probing_hash_table_benchmark
bicleaner_hardrules-2.10.8.data/data/bin/query
bicleaner_hardrules-2.10.8.data/data/include/kenlm/lm/bhiksha.hh
bicleaner_hardrules-2.10.8.data/data/include/kenlm/lm/binary_format.hh
bicleaner_hardrules-2.10.8.data/data/include/kenlm/lm/blank.hh
bicleaner_hardrules-2.10.8.data/data/include/kenlm/lm/config.hh
bicleaner_hardrules-2.10.8.data/data/include/kenlm/lm/enumerate_vocab.hh
bicleaner_hardrules-2.10.8.data/data/include/kenlm/lm/facade.hh
bicleaner_hardrules-2.10.8.data/data/include/kenlm/lm/left.hh
bicleaner_hardrules-2.10.8.data/data/include/kenlm/lm/lm_exception.hh
bicleaner_hardrules-2.10.8.data/data/include/kenlm/lm/max_order.hh
bicleaner_hardrules-2.10.8.data/data/include/kenlm/lm/model.hh
bicleaner_hardrules-2.10.8.data/data/include/kenlm/lm/model_type.hh
bicleaner_hardrules-2.10.8.data/data/include/kenlm/lm/ngram_query.hh
bicleaner_hardrules-2.10.8.data/data/include/kenlm/lm/partial.hh
bicleaner_hardrules-2.10.8.data/data/include/kenlm/lm/quantize.hh
bicleaner_hardrules-2.10.8.data/data/include/kenlm/lm/read_arpa.hh
bicleaner_hardrules-2.10.8.data/data/include/kenlm/lm/return.hh
bicleaner_hardrules-2.10.8.data/data/include/kenlm/lm/search_hashed.hh
bicleaner_hardrules-2.10.8.data/data/include/kenlm/lm/search_trie.hh
bicleaner_hardrules-2.10.8.data/data/include/kenlm/lm/sizes.hh
bicleaner_hardrules-2.10.8.data/data/include/kenlm/lm/state.hh
bicleaner_hardrules-2.10.8.data/data/include/kenlm/lm/trie.hh
bicleaner_hardrules-2.10.8.data/data/include/kenlm/lm/trie_sort.hh
bicleaner_hardrules-2.10.8.dist-info/METADATA
bicleaner_hardrules-2.10.8.dist-info/WHEEL
bicleaner_hardrules-2.10.8.dist-info/entry_points.txt
bicleaner_hardrules-2.10.8.dist-info/top_level.txt
bicleaner_hardrules-2.10.8.dist-info/RECORD
bicleaner_hardrules-2.10.8.dist-info/licenses/LICENSE
