Metadata-Version: 2.4
Name: bicleaner-hardrules
Version: 2.10.8
Summary: Pre-filtering step for obvious noise based on rules, poor language based on general language modelling and vulgar language based on specific language modelling
Author-email: Prompsit Language Engineering <info@prompsit.com>
Maintainer-email: Jaume Zaragoza <jzaragoza@prompsit.com>
Project-URL: HomePage, https://github.com/bitextor/bicleaner-hardrules
Project-URL: Prompsit Language Engineering, http://www.prompsit.com
Project-URL: Paracrawl, https://paracrawl.eu/
Project-URL: MaCoCu, https://macocu.eu
Project-URL: HPLT Project, https://hplt-project.org
Classifier: Environment :: Console
Classifier: Intended Audience :: Science/Research
Classifier: Programming Language :: Python :: 3.7
Classifier: Programming Language :: Python :: 3.8
Classifier: Programming Language :: Python :: 3.9
Classifier: Programming Language :: Python :: 3.10
Classifier: License :: OSI Approved :: GNU General Public License v3 (GPLv3)
Classifier: Operating System :: POSIX :: Linux
Classifier: Topic :: Text Processing :: Linguistic
Classifier: Topic :: Software Development :: Libraries :: Python Modules
Classifier: Topic :: Text Processing :: Filters
Requires-Python: >=3.8
License-File: LICENSE
Requires-Dist: regex
Requires-Dist: PyYAML
Requires-Dist: pytest
Requires-Dist: toolwrapper<=3,>=1.0
Requires-Dist: joblib
Requires-Dist: sacremoses==0.0.53
Requires-Dist: fasttext-wheel==0.9.2
Requires-Dist: fastspell==0.11.1
Requires-Dist: huggingface-hub<2,>=0.15
Dynamic: license-file
